tmutils
