Metadata-Version: 2.4
Name: tmutils
Version: 0.49.39
Summary: Basic Module Operations
Requires-Python: >=3.6
Requires-Dist: requests
Requires-Dist: urllib3<2
Requires-Dist: beautifulsoup4
Requires-Dist: tqdm
Requires-Dist: schedule
Requires-Dist: dbutils
Requires-Dist: pymysql
Requires-Dist: lark_oapi
